ubuntu_utils/__init__.py
ubuntu_utils/commands.py
ubuntu_utils/configs.template.py
ubuntu_utils/file_server.py
ubuntu_utils/get_apt_packages.json
ubuntu_utils/get_apt_packages.py
ubuntu_utils/run.py
ubuntu_utils/run.sh
ubuntu_utils/framework/duplicate_check.py
ubuntu_utils/framework/execution_recorder.py
ubuntu_utils/framework/process.py
ubuntu_utils/framework/remote.py
ubuntu_utils/framework/settings.py
ubuntu_utils/framework/ssh.py
ubuntu_utils/framework/utils.py
ubuntu_utils/framework/lib/__init__.py
ubuntu_utils/framework/lib/file_utils.py
ubuntu_utils/framework/lib/network_utils.py
ubuntu_utils/framework/lib/other_utils.py
ubuntu_utils/framework/lib/serialization_utils.py
ubuntu_utils/resources/01-network-manager-all.original.yaml
ubuntu_utils/resources/01-network-manager-all.yaml
ubuntu_utils/resources/apt-offline_1.8.6-1_all.deb
ubuntu_utils/resources/custom-resources.yaml
ubuntu_utils/resources/daemon.json
ubuntu_utils/resources/kubeadm-config.yaml
ubuntu_utils/scripts/__init__.py
ubuntu_utils/scripts/apt-offline-sh
ubuntu_utils/scripts/build-efi
ubuntu_utils/scripts/c-m-part
ubuntu_utils/scripts/ch-grub-menu
ubuntu_utils/scripts/chswap
ubuntu_utils/scripts/chtext
ubuntu_utils/scripts/enable-hibernate
ubuntu_utils/scripts/free-space
ubuntu_utils/scripts/get-cert
ubuntu_utils/scripts/get_docker_file
ubuntu_utils/scripts/m-part
ubuntu_utils/scripts/resize-part
ubuntu_utils/scripts/shortcut
ubuntu_utils/scripts/xz-docker
ubuntu_utils/scripts/lib/__init__.py
ubuntu_utils/scripts/lib/get_docker_file.py
ubuntu_utils/scripts/lib/init.py
ubuntu_utils/scripts/lib/myshlib
ubuntu_utils-1.1.0.dist-info/METADATA
ubuntu_utils-1.1.0.dist-info/WHEEL
ubuntu_utils-1.1.0.dist-info/entry_points.txt
ubuntu_utils-1.1.0.dist-info/top_level.txt
ubuntu_utils-1.1.0.dist-info/RECORD
