Metadata-Version: 2.4
Name: ubuntu_utils
Version: 1.1.0
Summary: Ubuntu utils
Author-email: sleeping-in-bed <nyanyanyaworld@gmail.com>
Classifier: Programming Language :: Python
Classifier: Programming Language :: Python :: 3 :: Only
Classifier: Programming Language :: Python :: 3.10
Classifier: Programming Language :: Python :: 3.11
Classifier: Programming Language :: Python :: 3.12
Classifier: Programming Language :: Python :: 3.13
Classifier: Operating System :: OS Independent
Requires-Python: >=3.10
Requires-Dist: docker>=7.1.0
Requires-Dist: paramiko>=3.5.1
Requires-Dist: scp>=0.15.0
Requires-Dist: types-colorama>=0.4.15.20240311
Requires-Dist: types-docker>=7.1.0.20250523
Requires-Dist: types-paramiko>=3.5.0.20250516
Requires-Dist: types-pyyaml>=6.0.12.20250516
Requires-Dist: types-requests>=2.32.0.20250602
